destimator/__init__.py
destimator/described_estimator.py
destimator/utils.py
destimator/tests/__init__.py
destimator/tests/test.py
destimator-0.1.4.dist-info/DESCRIPTION.rst
destimator-0.1.4.dist-info/METADATA
destimator-0.1.4.dist-info/RECORD
destimator-0.1.4.dist-info/WHEEL
destimator-0.1.4.dist-info/metadata.json
destimator-0.1.4.dist-info/top_level.txt
