Metadata-Version: 2.0
Name: destimator
Version: 0.1.4
Summary: A metadata-saving proxy for scikit-learn etimators.
Home-page: https://github.com/rainforestapp/destimator
Author: Maciej Gryka
Author-email: maciej@rainforestqa.com
License: MIT
Keywords: scikit-learn,machine-learning,data,science
Platform: UNKNOWN
Classifier: Development Status :: 3 - Alpha
Classifier: Intended Audience :: Developers
Classifier: Natural Language :: English
Classifier: License :: OSI Approved :: MIT License
Classifier: Operating System :: OS Independent
Classifier: Programming Language :: Python
Classifier: Programming Language :: Python :: 2
Classifier: Programming Language :: Python :: 2.7
Classifier: Programming Language :: Python :: 3
Classifier: Programming Language :: Python :: 3.5
Classifier: Topic :: Scientific/Engineering :: Artificial Intelligence
Requires-Dist: numpy (>=1.10.1)
Requires-Dist: requests (>=2.8.1)
Requires-Dist: scikit-learn (>=0.17)
Requires-Dist: scipy (>=0.16.0)
Provides-Extra: dev
Requires-Dist: check-manifest; extra == 'dev'
Requires-Dist: sphinx; extra == 'dev'
Requires-Dist: sphinx-rtd-theme; extra == 'dev'
Requires-Dist: twine; extra == 'dev'
Provides-Extra: test
Requires-Dist: flake8; extra == 'test'
Requires-Dist: pytest; extra == 'test'
Requires-Dist: pytest-cov; extra == 'test'
Requires-Dist: tox; extra == 'test'
